odoo/addons/l10n_it_abicab/README.rst
odoo/addons/l10n_it_abicab/__init__.py
odoo/addons/l10n_it_abicab/__manifest__.py
odoo/addons/l10n_it_abicab/i18n/de.po
odoo/addons/l10n_it_abicab/i18n/it.po
odoo/addons/l10n_it_abicab/i18n/nb_NO.po
odoo/addons/l10n_it_abicab/i18n/sl.po
odoo/addons/l10n_it_abicab/models/__init__.py
odoo/addons/l10n_it_abicab/models/abicab.py
odoo/addons/l10n_it_abicab/tests/__init__.py
odoo/addons/l10n_it_abicab/tests/test_abicab.py
odoo/addons/l10n_it_abicab/views/abicab_view.xml
odoo11_addon_l10n_it_abicab-11.0.1.0.0.dist-info/DESCRIPTION.rst
odoo11_addon_l10n_it_abicab-11.0.1.0.0.dist-info/METADATA
odoo11_addon_l10n_it_abicab-11.0.1.0.0.dist-info/RECORD
odoo11_addon_l10n_it_abicab-11.0.1.0.0.dist-info/WHEEL
odoo11_addon_l10n_it_abicab-11.0.1.0.0.dist-info/metadata.json
odoo11_addon_l10n_it_abicab-11.0.1.0.0.dist-info/top_level.txt
